LICENSE.txt
MANIFEST.in
README.md
pyproject.toml
setup.py
DiscordUtilsv2/InviteTracker.py
DiscordUtilsv2/Music.py
DiscordUtilsv2/Pagination.py
DiscordUtilsv2/__init__.py
DiscordUtilsv2.egg-info/PKG-INFO
DiscordUtilsv2.egg-info/SOURCES.txt
DiscordUtilsv2.egg-info/dependency_links.txt
DiscordUtilsv2.egg-info/requires.txt
DiscordUtilsv2.egg-info/top_level.txt