Metadata-Version: 2.1
Name: DiscordUtilsv2
Version: 1.3.5
Summary: DiscordUtils is a very useful library made to be used with discord.py. EpikHost took it over as the maintainer was no longer active.
Home-page: https://www.github.com/EpikHost/DiscordUtils
Author: toxicrecker & EpikHost
License: UNKNOWN
Platform: UNKNOWN
Classifier: Programming Language :: Python :: 3
Classifier: License :: OSI Approved :: MIT License
Classifier: Operating System :: OS Independent
Requires-Python: >= 3.6
Provides-Extra: voice
License-File: LICENSE.txt
